zfslib/__init__.py
zfslib/zfslib.py
zfslib-0.13.5.dist-info/LICENSE
zfslib-0.13.5.dist-info/METADATA
zfslib-0.13.5.dist-info/WHEEL
zfslib-0.13.5.dist-info/RECORD
